rbprof/__init__.py
rbprof/core/__init__.py
rbprof/core/alerter.py
rbprof/core/behavioral_engine.py
rbprof/core/detector.py
rbprof/core/monitor.py
rbprof/models/__init__.py
rbprof/models/behavioral_model.py
rbprof/utils/__init__.py
rbprof/utils/logger.py
rbprof-0.2.0.dist-info/LICENSE
rbprof-0.2.0.dist-info/METADATA
rbprof-0.2.0.dist-info/WHEEL
rbprof-0.2.0.dist-info/RECORD
