Metadata-Version: 2.3
Name: rbprof
Version: 0.2.0
Summary: cybersecurity framework designed for behavioral profiling and analysis of ransomware.
License: MIT
Author: Elton Tanaka Mukarati
Author-email: eltontanakamukarati@gmail.com
Requires-Python: >=3.8,<4.0
Classifier: License :: OSI Approved :: MIT License
Classifier: Programming Language :: Python :: 3
Classifier: Programming Language :: Python :: 3.8
Classifier: Programming Language :: Python :: 3.9
Classifier: Programming Language :: Python :: 3.10
Classifier: Programming Language :: Python :: 3.11
Classifier: Programming Language :: Python :: 3.12
Classifier: Programming Language :: Python :: 3.13
Requires-Dist: requests (>=2.25.1,<3.0.0)
